fullcontact/error.py
fullcontact/api_resource.py
fullcontact/test.py
fullcontact/__init__.py
fullcontact/company.py
fullcontact/person.py
fullcontact_python-1.0.0b1.dist-info/metadata.json
fullcontact_python-1.0.0b1.dist-info/WHEEL
fullcontact_python-1.0.0b1.dist-info/top_level.txt
fullcontact_python-1.0.0b1.dist-info/DESCRIPTION.rst
fullcontact_python-1.0.0b1.dist-info/METADATA
fullcontact_python-1.0.0b1.dist-info/RECORD
