Metadata-Version: 2.0
Name: fullcontact-python
Version: 1.0.0b1
Summary: FullContact API SDK for Python
Home-page: https://github.com/cyberlake/fullcontact-python
Author: Amil Osmanli
Author-email: amil@birdleaf.io
License: MIT
Platform: UNKNOWN
Classifier: Environment :: Web Environment
Classifier: Intended Audience :: Developers
Classifier: Operating System :: OS Independent
Classifier: Programming Language :: Python
Classifier: Programming Language :: Python :: 2.7
Classifier: Programming Language :: Python :: 3.4
Classifier: Topic :: Internet :: WWW/HTTP :: Dynamic Content
Classifier: Topic :: Software Development :: Libraries :: Python Modules
Requires-Dist: requests
